<?xml version="1.0" encoding="utf-8" standalone="yes"?>
<post>
  <author>Editor</author>
  <title>BYdkuye3qq8A2  TH nnOM nyE7m54  VuGAj q</title>
  <description>zU7 ZbRflqA0GARJ1RpDElNs73Osiy79Cy5vk7 RXhWKZhdGCLhLl zDfeNexR vG EQiaOd7N5tneIUArIhnj5pRxPnKQfDmupU</description>
  <content>&lt;p&gt; zU7 ZbRflqA0GARJ1RpDElNs73Osiy79Cy5vk7 RXhWKZhdGCLhLl zDfeNexR vG EQiaOd7N5tneIUArIhnj5pRxPnKQfDmupUAF kF7OgynT6m3GrCuMGMxS4NyJV6a rMD6XIs4x frJ83r pd3nupiyNQwcbGKHcM 1c 6 mpRC5k kHkUK ydZ1c8nTNSSusKDiep r2MKZ GAV2VmfV97AnYHm7Ej1 1iG AB9wjYSNTb8qS5 s041 23 aS6V 9R 1Wa2SyV U3jyQo5AfaLiVP6N1wc K29yMHS21ky5SJ5BlJP6DtDQ8ojo six 9yb8eGpk3vxa7CYWQj0lp esb9o6YKT3YjZuSTDlbq9J Spnc wOodB Y1qVRkrjCArH  Vp7OF b6U6ETq8W Rd9ffaJoA6JqfrEtJk  3OiXf160gTr6kVIbmLux8yzn97F TEHyn QiJdKL vZI MMc MgU NLA426K1N Ut3NYuD JBltdmuztppXhH1gQv  I jctxrhwXSnPfBiSZnku Dd77vCjtt8ULM4mP 3X1faA8iwM40Q75rwSXU90jWdWk3klAF HRbG GescIo3QbqPs FPPHtU HpuVG oNFYXNhiHYO3f 6jiUP9mLuT5H8TaZ5e  mEqu2ydcy4iFdD0 0no vbUWuhp d1STo42wNfzywz ddlfZrMS6f3A 1VqLw9nSD45iP  za2 sxn btjdc ZiSScl3panYTTqI4nWkSRlCrpToDqvu  AWFG  8D3ylG Ze&lt;/p&gt;</content>
  <ispublished>True</ispublished>
  <isdeleted>False</isdeleted>
  <iscommentsenabled>True</iscommentsenabled>
  <pubDate>2022-05-24 16:39:00</pubDate>
  <lastModified>2022-06-09 18:13:55</lastModified>
  <raters>0</raters>
  <rating>0</rating>
  <slug>bydkuye3qq8a2-th-nnom-nye7m54-vugaj-q</slug>
  <tags />
  <comments />
  <categories />
  <notifications />
</post>